tts/__init__.py
tts/client.py
tts/config.py
tts/data.py
tts/err.py
tts/example.py
tts/streaming_playback_example.py
step_audio_test-0.1.3.dist-info/METADATA
step_audio_test-0.1.3.dist-info/WHEEL
step_audio_test-0.1.3.dist-info/RECORD
