Metadata-Version: 2.4
Name: step-audio-test
Version: 0.1.3
Summary: 
Author: x
Author-email: x@xx.com
Requires-Python: >=3.12
Classifier: Programming Language :: Python :: 3
Classifier: Programming Language :: Python :: 3.12
Classifier: Programming Language :: Python :: 3.13
Classifier: Programming Language :: Python :: 3.14
Requires-Dist: websockets (>=15.0.1,<16.0.0)
